src/j2/reg/dffn.v
module dffn (
    Q,D,ck
);
    parameter N = 1;

    input [N-1:0] D;
    input ck;
    output [N-1:0] Q;
    reg [N-1:0] Q;
    initial
        Q = {N{1'b0}};
    always @(negedge ck)
        Q = D;
endmodule

src/j2/reg/count.v
module count (
    a,ck,b
);
    input a, ck;
    output b;
    wire na;
    wire s1, s2, t;
    wire d1, d2, d3, d4;
    wire e1, e2, e3;
    dffn f1(s1,d1,ck);
    dffn f2(s2,e1,ck);
    assign na = ~a;
    assign ns1 = ~s1;
    assign ns2 = ~s2;

    assign d4 = s1 & ns2, d3 = na & s1, d2 = a & ns1 & s2, d1 = d4 | d3 | d2;
    assign e3 = na & s2, e2 = a & ns2, e1 = e3 | e2;
    assign b = a & s1 & s2;
endmodule

src/j2/reg/clk.v
module clk (
    ck
);
    output ck;
    reg ck;
    initial ck = 0;
    always #50 ck = ~ck;
endmodule

src/j2/reg/countSim.v
module countSim;
    reg a;
    wire b;

    clk clk1(ck);
    count dut (a,ck,b);

    initial
        begin
        $dumpfile("countSim.vcd");
        $dumpvars(0, countSim);
        $monitor("%b  %b %b  %b  %b", a, ck, b, dut.s1, dut.s2, $stime);
        $display("a ck b s1 s2       time");

        a = 0;
        #100 a = 1;
        #100 a = 0;
        #100 a = 1;
        #100 a = 0;
        #100 a = 1;
        #100 a = 0;
        #100 a = 1;
        #100 a = 0;
        $finish;
        end
endmodule

src/j2/reg/countSim.vcd
$date
	Wed Jul 10 15:04:35 2024
$end
$version
	Icarus Verilog
$end
$timescale
	1s
$end
$scope module countSim $end
$var wire 1 ! ck $end
$var wire 1 " b $end
$var reg 1 # a $end
$scope module clk1 $end
$var reg 1 ! ck $end
$upscope $end
$scope module dut $end
$var wire 1 # a $end
$var wire 1 " b $end
$var wire 1 ! ck $end
$var wire 1 $ d1 $end
$var wire 1 % d2 $end
$var wire 1 & d3 $end
$var wire 1 ' d4 $end
$var wire 1 ( e1 $end
$var wire 1 ) e2 $end
$var wire 1 * e3 $end
$var wire 1 + na $end
$var wire 1 , ns1 $end
$var wire 1 - ns2 $end
$var wire 1 . s2 $end
$var wire 1 / s1 $end
$scope module f1 $end
$var wire 1 $ D $end
$var wire 1 ! ck $end
$var reg 1 / Q $end
$upscope $end
$scope module f2 $end
$var wire 1 ( D $end
$var wire 1 ! ck $end
$var reg 1 . Q $end
$upscope $end
$upscope $end
$upscope $end
$enddefinitions $end
$comment Show the parameter values. $end
$dumpall
$end
#0
$dumpvars
0/
0.
1-
1,
1+
0*
0)
0(
0'
0&
0%
0$
0#
0"
0!
$end
#50
1!
#100
1(
0+
1)
0!
1#
#150
1!
#200
0-
1*
1(
1.
1+
0)
0!
0#
#250
1!
#300
0(
1$
0*
1%
0+
0!
1#
#350
1!
#400
1'
1$
1-
0,
1&
0%
0.
1/
1+
0!
0#
#450
1!
#500
0&
1(
0+
1)
0!
1#
#550
1!
#600
0'
0-
1&
1*
1(
1.
1+
0)
0!
0#
#650
1!
#700
0$
0(
0&
0*
1"
0+
0!
1#
#750
1!
#800
1-
1,
0"
0.
0/
1+
0!
0#
