src/j2/eq.v
module eq (
    s,a,b
);
    input a, b;
    output s;
    wire na, nb, s1, s2;
    assign na = ~a, nb = ~b;
    assign s1 = a & b, s2 = na & nb;
    assign s = s1 | s2;
endmodule

src/j2/doubleEq.v
module doubleEq(
    s,a,b,c,d
);
    input a, b, c, d;
    output s;
    wire w1, w2;
    eq m1(w1, a, b);
    eq m2(w2, c, d);
    assign s = w1 & w2;
endmodule

src/j2/doubleEqSim.v
module doubleEqSim; /* 一致検出回路の */
    wire s; /* シミュレーション */
    reg a, b, c, d;
    doubleEq g1(s, a, b, c, d);
    initial
        begin
        $dumpfile("doubleEq.vcd");
        $dumpvars(0, doubleEqSim);
        $monitor(" %b %b %b %b %b %b  %b", a, b, c, d, s, g1.w1, g1.w2, $stime);
        $display(" a b c d s w1 w2       time");
        /* test all case */
        a=0; b=0; c=0; d=0;
        #50 a=0; b=0; c=0; d=1;
        #50 a=0; b=0; c=1; d=0;
        #50 a=0; b=0; c=1; d=1;
        #50 a=0; b=1; c=0; d=0;
        #50 a=0; b=1; c=0; d=1;
        #50 a=0; b=1; c=1; d=0;
        #50 a=0; b=1; c=1; d=1;
        #50 a=1; b=0; c=0; d=0;
        #50 a=1; b=0; c=0; d=1;
        #50 a=1; b=0; c=1; d=0;
        #50 a=1; b=0; c=1; d=1;
        #50 a=1; b=1; c=0; d=0;
        #50 a=1; b=1; c=0; d=1;
        #50 a=1; b=1; c=1; d=0;
        #50 a=1; b=1; c=1; d=1;
        end
endmodule

src/j2/doubleEq.vcd
$date
	Wed Jul  3 14:06:47 2024
$end
$version
	Icarus Verilog
$end
$timescale
	1s
$end
$scope module doubleEqSim $end
$var wire 1 ! s $end
$var reg 1 " a $end
$var reg 1 # b $end
$var reg 1 $ c $end
$var reg 1 % d $end
$scope module g1 $end
$var wire 1 " a $end
$var wire 1 # b $end
$var wire 1 $ c $end
$var wire 1 % d $end
$var wire 1 ! s $end
$var wire 1 & w2 $end
$var wire 1 ' w1 $end
$scope module m1 $end
$var wire 1 " a $end
$var wire 1 # b $end
$var wire 1 ( na $end
$var wire 1 ) nb $end
$var wire 1 ' s $end
$var wire 1 * s1 $end
$var wire 1 + s2 $end
$upscope $end
$scope module m2 $end
$var wire 1 $ a $end
$var wire 1 % b $end
$var wire 1 , na $end
$var wire 1 - nb $end
$var wire 1 & s $end
$var wire 1 . s1 $end
$var wire 1 / s2 $end
$upscope $end
$upscope $end
$upscope $end
$enddefinitions $end
$comment Show the parameter values. $end
$dumpall
$end
#0
$dumpvars
1/
0.
1-
1,
1+
0*
1)
1(
1'
1&
0%
0$
0#
0"
1!
$end
#50
0!
0&
0/
0-
1%
#100
1-
0,
0%
1$
#150
1!
1&
0-
1.
1%
#200
0!
0'
1/
1&
0+
1-
1,
0.
0)
0%
0$
1#
#250
0&
0/
0-
1%
#300
1-
0,
0%
1$
#350
1&
0-
1.
1%
#400
1/
1&
1-
1,
0.
1)
0(
0%
0$
0#
1"
#450
0&
0/
0-
1%
#500
1-
0,
0%
1$
#550
1&
0-
1.
1%
#600
1!
1/
1&
1'
1-
1,
0.
0)
1*
0%
0$
1#
#650
0!
0&
0/
0-
1%
#700
1-
0,
0%
1$
#750
1!
1&
0-
1.
1%
